pysosiriusmongo/__init__.py
pysosiriusmongo/poll_channels.py
pysosiriusmongo/setup.py
pysosiriusmongo/etl/__init__.py
pysosiriusmongo/etl/extract_transform_load.py
pysosiriusmongo-0.1.2.dist-info/DESCRIPTION.rst
pysosiriusmongo-0.1.2.dist-info/METADATA
pysosiriusmongo-0.1.2.dist-info/RECORD
pysosiriusmongo-0.1.2.dist-info/WHEEL
pysosiriusmongo-0.1.2.dist-info/metadata.json
pysosiriusmongo-0.1.2.dist-info/top_level.txt
