Metadata-Version: 2.0
Name: pysosiriusmongo
Version: 0.1.2
Summary: PySoSirius SiriusXM Song Storage
Home-page: https://github.com/T-Santos/PySoSiriusMongo
Author: Tyler Santos
Author-email: 1tsantos7+pysosirius@Gmail.com
License: MIT
Keywords: Sirius SiriusXM XM Music MongoDB
Platform: UNKNOWN
Classifier: Development Status :: 1 - Planning
Classifier: Intended Audience :: Developers
Classifier: License :: OSI Approved :: MIT License
Classifier: Programming Language :: Python :: 2.7
Requires-Dist: pysosirius
Requires-Dist: pymongo
